.DS_Store
surferai/__init__.py
tests/__init__.py
tests/test_myfunctions.py
surferai-0.1.7.dist-info/LICENSE
surferai-0.1.7.dist-info/METADATA
surferai-0.1.7.dist-info/WHEEL
surferai-0.1.7.dist-info/entry_points.txt
surferai-0.1.7.dist-info/top_level.txt
surferai-0.1.7.dist-info/RECORD
