Metadata-Version: 2.1
Name: surferai
Version: 0.1.7
Summary: The official Python library for the Surfer HumanAPI
Home-page: https://github.com/CEREBRUS-MAXIMUS/surfer-python
Author: Me
Author-email: Jack Blair <jackblairing@gmail.com>
License: MIT License        
Project-URL: Homepage, https://github.com/CEREBRUS-MAXIMUS/surfer-python
Project-URL: Repository, https://github.com/CEREBRUS-MAXIMUS/surfer-python
Platform: UNKNOWN
Classifier: Typing :: Typed
Classifier: Intended Audience :: Developers
Classifier: Programming Language :: Python :: 3.7
Classifier: Programming Language :: Python :: 3.8
Classifier: Programming Language :: Python :: 3.9
Classifier: Programming Language :: Python :: 3.10
Classifier: Programming Language :: Python :: 3.11
Classifier: Programming Language :: Python :: 3.12
Classifier: Operating System :: OS Independent
Classifier: Operating System :: POSIX
Classifier: Operating System :: MacOS
Classifier: Operating System :: POSIX :: Linux
Classifier: Operating System :: Microsoft :: Windows
Classifier: Topic :: Software Development :: Libraries :: Python Modules
Classifier: License :: OSI Approved :: Apache Software License
Requires-Python: >=3.7.1
License-File: LICENSE
Requires-Dist: httpx (<1,>=0.23.0)
Requires-Dist: pydantic (<3,>=1.9.0)
Requires-Dist: typing-extensions (<5,>=4.7)
Requires-Dist: anyio (<5,>=3.5.0)
Requires-Dist: distro (<2,>=1.7.0)
Requires-Dist: sniffio
Requires-Dist: requests
Provides-Extra: datalib
Requires-Dist: numpy (>=1) ; extra == 'datalib'
Requires-Dist: pandas (>=1.2.3) ; extra == 'datalib'
Requires-Dist: pandas-stubs (>=1.1.0.11) ; extra == 'datalib'
